overlay/__init__.py
overlay/window.py
overlay/template/__init__.py
overlay/template/asset_finder.py
overlay/template/futuristic.py
overlay/template/prefab.py
py_tkoverlay-1.1.0.dist-info/LICENSE
py_tkoverlay-1.1.0.dist-info/METADATA
py_tkoverlay-1.1.0.dist-info/WHEEL
py_tkoverlay-1.1.0.dist-info/top_level.txt
py_tkoverlay-1.1.0.dist-info/RECORD
