Metadata-Version: 2.1
Name: py-tkoverlay
Version: 1.1.0
Summary: A package that creates and manipulates screen overlays based on tkinter.
Home-page: https://github.com/KavyanshKhaitan2/py-tkoverlay
Author: Kavyansh Khaitan
Author-email: kavyanshkhaitan11@gmail.com
License: MIT
License-File: LICENSE
